RSO/__init__.py
RSO/base.py
RSO/index.py
RSO/model.py
RSO/asyncio/__init__.py
RSO/asyncio/index.py
RSO/asyncio/model.py
RSO/txredisapi/__init__.py
RSO/txredisapi/index.py
RSO/txredisapi/model.py
redis_simple_orm-3.0.0.data/data/LICENSE
redis_simple_orm-3.0.0.dist-info/licenses/LICENSE
redis_simple_orm-3.0.0.dist-info/METADATA
redis_simple_orm-3.0.0.dist-info/WHEEL
redis_simple_orm-3.0.0.dist-info/top_level.txt
redis_simple_orm-3.0.0.dist-info/RECORD
