Metadata-Version: 2.4
Name: redis_simple_orm
Version: 3.0.0
Summary: Simple Redis ORM (Sync and Async).
Home-page: https://github.com/jockerz/redis_simple_orm
Author: Jockerz
Author-email: jockerz@protonmail.com
License: MIT
Classifier: Development Status :: 3 - Alpha
Classifier: Environment :: Console
Classifier: Intended Audience :: Developers
Classifier: License :: OSI Approved :: MIT License
Classifier: Operating System :: OS Independent
Classifier: Programming Language :: Python :: 3
Classifier: Programming Language :: Python :: 3.8
Classifier: Programming Language :: Python :: 3.9
Classifier: Programming Language :: Python :: 3.10
Requires-Python: >=3.8
License-File: LICENSE
Requires-Dist: aiocontextvars; python_version < "3.7"
Provides-Extra: all
Requires-Dist: redis; extra == "all"
Requires-Dist: pyopenssl; extra == "all"
Requires-Dist: txredisapi; extra == "all"
Provides-Extra: redis-py
Requires-Dist: redis; extra == "redis-py"
Provides-Extra: txredisapi
Requires-Dist: pyopenssl; extra == "txredisapi"
Requires-Dist: txredisapi; extra == "txredisapi"
Dynamic: author
Dynamic: author-email
Dynamic: classifier
Dynamic: description
Dynamic: description-content-type
Dynamic: home-page
Dynamic: license
Dynamic: license-file
Dynamic: provides-extra
Dynamic: requires-dist
Dynamic: requires-python
Dynamic: summary
